ClappScrapers/__init__.py
ClappScrapers/asunnot/__init__.py
ClappScrapers/asunnot/spider/__init__.py
ClappScrapers/asunnot/spider/asunnotrentapispider.py
ClappScrapers/asunnot/spider/asunnotsellapispider.py
ClappScrapers/asunnot/spider/asunnotsellspider.py
ClappScrapers/asunnot/spider/asunnotspider.py
ClappScrapers/asunnot/spider/extension.py
ClappScrapers/asunnot/spider/items.py
ClappScrapers/asunnot/spider/middlewares.py
ClappScrapers/asunnot/spider/pipelines.py
ClappScrapers/asunnot/spider/settings.py
ClappScrapers/den_boligsiden_sell/__init__.py
ClappScrapers/den_boligsiden_sell/spider/__init__.py
ClappScrapers/den_boligsiden_sell/spider/boligsidendailyspider.py
ClappScrapers/den_boligsiden_sell/spider/boligsidensellingspider.py
ClappScrapers/den_boligsiden_sell/spider/extension.py
ClappScrapers/den_boligsiden_sell/spider/items.py
ClappScrapers/den_boligsiden_sell/spider/middlewares.py
ClappScrapers/den_boligsiden_sell/spider/pipelines.py
ClappScrapers/den_boligsiden_sell/spider/settings.py
ClappScrapers/den_rental/__init__.py
ClappScrapers/den_rental/spider/__init__.py
ClappScrapers/den_rental/spider/boligportalspider.py
ClappScrapers/den_rental/spider/extension.py
ClappScrapers/den_rental/spider/items.py
ClappScrapers/den_rental/spider/middlewares.py
ClappScrapers/den_rental/spider/newboligspider.py
ClappScrapers/den_rental/spider/pipelines.py
ClappScrapers/den_rental/spider/settings.py
ClappScrapers/fin_rental/__init__.py
ClappScrapers/fin_rental/spider/__init__.py
ClappScrapers/fin_rental/spider/extension.py
ClappScrapers/fin_rental/spider/finlandrentalspider.py
ClappScrapers/fin_rental/spider/items.py
ClappScrapers/fin_rental/spider/middlewares.py
ClappScrapers/fin_rental/spider/pipelines.py
ClappScrapers/fin_rental/spider/settings.py
ClappScrapers/funda_scraper/__init__.py
ClappScrapers/funda_scraper/preprocess.py
ClappScrapers/funda_scraper/scrape.py
ClappScrapers/funda_scraper/utils.py
ClappScrapers/funda_scraper/config/__init__.py
ClappScrapers-0.2.51.dist-info/LICENSE
ClappScrapers-0.2.51.dist-info/METADATA
ClappScrapers-0.2.51.dist-info/WHEEL
ClappScrapers-0.2.51.dist-info/top_level.txt
ClappScrapers-0.2.51.dist-info/RECORD
