Metadata-Version: 2.2
Name: ClappScrapers
Version: 0.2.51
Summary: Clappform Python scraper
Home-page: https://github.com/ClappFormOrg/clappform-scraper
Author: Clappform B.V.
Author-email: info@clappform.com
License: MIT
Keywords: scraper
Classifier: Development Status :: 4 - Beta
Classifier: License :: OSI Approved :: MIT License
Classifier: Programming Language :: Python :: 3
Classifier: Operating System :: OS Independent
Requires-Python: >=3.10
License-File: LICENSE
Requires-Dist: scrapy
Requires-Dist: scrapy-fake-useragent
Requires-Dist: beautifulsoup4>=4.8
Requires-Dist: requests>=2
Requires-Dist: diot>=0.1.5
Requires-Dist: PyYAML>=5.0
Requires-Dist: tqdm>=4.42.0
Requires-Dist: pandas>=1.2
Requires-Dist: lxml>=4
Requires-Dist: urllib3==1.26
Requires-Dist: scrapeops-scrapy==0.5.2
Requires-Dist: scrapeops-scrapy-proxy-sdk==1.0
Dynamic: author
Dynamic: author-email
Dynamic: classifier
Dynamic: description
Dynamic: description-content-type
Dynamic: home-page
Dynamic: keywords
Dynamic: license
Dynamic: requires-dist
Dynamic: requires-python
Dynamic: summary
